[
   {
      "URL": "/About Me/Projects/Server/Hardware/2 Port SATA Controller/Listing_files/iu3_data/index.json",
      "Visible": false,
      "Title": "index",
      "SRC": "None",
      "Path": "E:/Website/Root/About Me/Projects/Server/Hardware/2 Port SATA Controller/Listing_files/iu3_data/index.json"
   },
   {
      "URL": "/About Me/Projects/Server/Hardware/2 Port SATA Controller/Listing_files/iu3_data/pr.htm",
      "Visible": true,
      "Title": "pr",
      "SRC": "None",
      "Path": "E:/Website/Root/About Me/Projects/Server/Hardware/2 Port SATA Controller/Listing_files/iu3_data/pr.htm"
   },
   {
      "URL": "/About Me/Projects/Server/Hardware/2 Port SATA Controller/Listing_files/iu3_data/pr_data/",
      "Visible": true,
      "Title": "pr_data",
      "SRC": "None",
      "Path": "E:/Website/Root/About Me/Projects/Server/Hardware/2 Port SATA Controller/Listing_files/iu3_data/pr_data/"
   }
]